jrpytests/__init__.py
jrpytests/__version__.py
jrpytests/flake8_config.ini
jrpytests/get_name_from_toml_file.py
jrpytests-0.1.6.dist-info/METADATA
jrpytests-0.1.6.dist-info/WHEEL
jrpytests-0.1.6.dist-info/RECORD
