Metadata-Version: 2.1
Name: jrpytests
Version: 0.1.6
Summary: 
Author: Jumping Rivers
Author-email: info@jumpingrivers.com
Requires-Python: >=3.9,<4.0
Classifier: Programming Language :: Python :: 3
Classifier: Programming Language :: Python :: 3.9
Classifier: Programming Language :: Python :: 3.10
Classifier: Programming Language :: Python :: 3.11
Classifier: Programming Language :: Python :: 3.12
Classifier: Programming Language :: Python :: 3.13
Requires-Dist: flake8 (>=3.9.1,<4.0.0)
Requires-Dist: pytest (>=6.2.5,<7.0.0)
